cdm/__init__.py
cdm/__main__.py
cdm/fio_cdm.py
cdmpy-0.3.2.dist-info/LICENSE
cdmpy-0.3.2.dist-info/METADATA
cdmpy-0.3.2.dist-info/WHEEL
cdmpy-0.3.2.dist-info/entry_points.txt
cdmpy-0.3.2.dist-info/top_level.txt
cdmpy-0.3.2.dist-info/RECORD
