Metadata-Version: 2.1
Name: cdmpy
Version: 0.3.2
Summary: A python script to generate CrystalDiskMark-style test result with fio. Should work across multi platforms.
Author-email: Lu Xu <oliver_lew@outlook.com>, Pyhoniasm <26092465+Pythoniasm@users.noreply.github.com>
License: MIT
Project-URL: repository, https://github.com/Pythoniasm/cdmpy
Keywords: CrystalDiskMark,disk utilities,hdd,ssd
Requires-Python: >=3.9.13
License-File: LICENSE
